{
    "size": [30, 30],
    "robots": [
        { "type": "castle", "team": 0, "x": 5, "y": 5 },
        { "type": "archeryRange", "team": 0, "x": 0, "y": 4 },
        {
            "type": "village",
            "team": 0,
            "x": 2,
            "y": 2,
            "resources": { "metal": 400 }
        },
        { "type": "siegeFoundry", "team": 0, "x": 4, "y": 4 },

        { "type": "castle", "team": 1, "x": 24, "y": 24 },
        { "type": "archeryRange", "team": 1, "x": 29, "y": 25 },
        {
            "type": "village",
            "team": 1,
            "x": 27,
            "y": 27,
            "resources": { "metal": 400 }
        },
        { "type": "siegeFoundry", "team": 1, "x": 25, "y": 25 },

        { "type": "castle", "team": 2, "x": 24, "y": 5 },
        { "type": "archeryRange", "team": 2, "x": 25, "y": 0 },
        {
            "type": "village",
            "team": 2,
            "x": 27,
            "y": 2,
            "resources": { "metal": 400 }
        },
        { "type": "siegeFoundry", "team": 2, "x": 25, "y": 4 },

        { "type": "castle", "team": 3, "x": 5, "y": 24 },
        { "type": "archeryRange", "team": 3, "x": 4, "y": 29 },
        {
            "type": "village",
            "team": 3,
            "x": 2,
            "y": 27,
            "resources": { "metal": 400 }
        },
        { "type": "siegeFoundry", "team": 3, "x": 4, "y": 25 }
    ],
    "sources": [
        { "type": "shallowQuarry", "x": 0, "y": 0 },
        { "type": "mineTin", "x": 5, "y": 0 },

        { "type": "shallowQuarry", "x": 29, "y": 29 },
        { "type": "mineTin", "x": 24, "y": 29 },

        { "type": "shallowQuarry", "x": 29, "y": 0 },
        { "type": "mineTin", "x": 29, "y": 5 },

        { "type": "shallowQuarry", "x": 0, "y": 29 },
        { "type": "mineTin", "x": 0, "y": 24 },

        { "type": "forest", "x": 14, "y": 14 },
        { "type": "forest", "x": 15, "y": 14 },
        { "type": "forest", "x": 15, "y": 15 },
        { "type": "forest", "x": 14, "y": 15 },
        { "type": "forest", "x": 13, "y": 13 },
        { "type": "forest", "x": 16, "y": 16 },
        { "type": "forest", "x": 13, "y": 16 },
        { "type": "forest", "x": 16, "y": 13 }
    ],
    "impassableSquares": [
        {"x" :14,"y": 1},
        {"x" :14,"y": 2},
        {"x" :14,"y": 3},
        {"x" :14,"y": 4},
        {"x" :14,"y": 5},
        {"x" :14,"y": 6},
        {"x" :14,"y": 7},
        {"x" :14,"y": 8},
        {"x" :14,"y": 9},
        {"x" :14,"y": 10},

        {"x" :1,"y": 15},
        {"x" :2,"y": 15},
        {"x" :3,"y": 15},
        {"x" :4,"y": 15},
        {"x" :5,"y": 15},
        {"x" :6,"y": 15},
        {"x" :7,"y": 15},
        {"x" :8,"y": 15},
        {"x" :9,"y": 15},
        {"x" :10,"y": 15},

        {"x" :28,"y": 14},
        {"x" :27,"y": 14},
        {"x" :26,"y": 14},
        {"x" :25,"y": 14},
        {"x" :24,"y": 14},
        {"x" :23,"y": 14},
        {"x" :22,"y": 14},
        {"x" :21,"y": 14},
        {"x" :20,"y": 14},
        {"x" :19,"y": 14},
        {"x" :18,"y": 14},

        {"x" :15,"y": 28},
        {"x" :15,"y": 27},
        {"x" :15,"y": 26},
        {"x" :15,"y": 25},
        {"x" :15,"y": 24},
        {"x" :15,"y": 23},
        {"x" :15,"y": 22},
        {"x" :15,"y": 21},
        {"x" :15,"y": 20},
        {"x" :15,"y": 19}
    ]
}
